{
  "repo": "zKauaFerreira/The-Gaming-Rumble",
  "branch": "games",
  "raw_base_url": "https://raw.githubusercontent.com/zKauaFerreira/The-Gaming-Rumble/games/torrents/",
  "total_games": 1686,
  "online_fix_total": 1686,
  "steam_with_metadata": 1573,
  "steam_without_metadata": 113,
  "match_rate": 93.3,
  "success_rate": 6.7,
  "online_fix_pages_total": 89,
  "pages_scraped_target": 89,
  "pages_present_in_json": 89,
  "last_page_in_json": 89,
  "new_games_found_this_run": 1837,
  "processed_games_this_run": 1686,
  "torrent_files_total": 2437,
  "json_entries_with_torrent": 1686,
  "last_scrape_at": "2026-04-24 19:28:41",
  "last_game_update": "2026-04-24T16:35:57+03:00",
  "generated_at": "2026-04-24 19:28:41"
}