{
  "repo": "zKauaFerreira/The-Gaming-Rumble",
  "branch": "games",
  "raw_base_url": "https://raw.githubusercontent.com/zKauaFerreira/The-Gaming-Rumble/games/torrents/",
  "total_games": 1710,
  "online_fix_total": 1710,
  "steam_with_metadata": 1599,
  "steam_without_metadata": 111,
  "match_rate": 93.51,
  "success_rate": 93.51,
  "online_fix_pages_total": 89,
  "pages_scraped_target": 89,
  "pages_present_in_json": 89,
  "last_page_in_json": 89,
  "new_games_found_this_run": 137,
  "latest_run_new_game_names": [
    "PEAK"
  ],
  "processed_games_this_run": 1,
  "torrent_files_total": 1710,
  "json_entries_with_torrent": 1710,
  "last_scrape_at": "2026-05-02 19:32:16",
  "last_scrape_at_display": "02/05/2026",
  "last_game_update": "2026-05-01T01:15:03+03:00",
  "generated_at": "2026-05-02 19:34:05",
  "generated_at_display": "02/05/2026"
}